pyWebCamWebServerMonitor/__init__.py
pyWebCamWebServerMonitor/commands.py
pyWebCamWebServerMonitor/settings.py
pyWebCamWebServerMonitor/api/__init__.py
pyWebCamWebServerMonitor/api/user.py
pyWebCamWebServerMonitor/api/webcam.py
pyWebCamWebServerMonitor/middleware/__init__.py
pyWebCamWebServerMonitor/middleware/auth.py
pyWebCamWebServerMonitor/models/__init__.py
pyWebCamWebServerMonitor/models/setting.py
pyWebCamWebServerMonitor/models/user.py
pyWebCamWebServerMonitor/res/webcamBusy.png
pyWebCamWebServerMonitor/routes/__init__.py
pyWebCamWebServerMonitor/web/static/android-chrome-192x192.png
pyWebCamWebServerMonitor/web/static/android-chrome-512x512.png
pyWebCamWebServerMonitor/web/static/apple-touch-icon.png
pyWebCamWebServerMonitor/web/static/favicon-16x16.png
pyWebCamWebServerMonitor/web/static/favicon-32x32.png
pyWebCamWebServerMonitor/web/static/favicon.ico
pyWebCamWebServerMonitor/web/static/index.html
pyWebCamWebServerMonitor/web/static/site.webmanifest
pyWebCamWebServerMonitor/web/static/css/app.be6dd2d4.css
pyWebCamWebServerMonitor/web/static/css/app.c030a1ae.css
pyWebCamWebServerMonitor/web/static/css/chunk-06c1cdb4.44dc43c3.css
pyWebCamWebServerMonitor/web/static/css/chunk-0799e2b4.104bef58.css
pyWebCamWebServerMonitor/web/static/css/chunk-1d5dbd58.1fc70c2a.css
pyWebCamWebServerMonitor/web/static/css/chunk-24f357a7.90cf9152.css
pyWebCamWebServerMonitor/web/static/css/chunk-3864bc5e.7ead00d7.css
pyWebCamWebServerMonitor/web/static/css/chunk-4daa49e2.058ffc1e.css
pyWebCamWebServerMonitor/web/static/css/chunk-4ea82cfb.4de5bb71.css
pyWebCamWebServerMonitor/web/static/css/chunk-60f5e58e.4533c763.css
pyWebCamWebServerMonitor/web/static/css/chunk-6727bfa8.103149d6.css
pyWebCamWebServerMonitor/web/static/css/chunk-68b2efeb.109e6a6b.css
pyWebCamWebServerMonitor/web/static/css/chunk-76528222.104bef58.css
pyWebCamWebServerMonitor/web/static/css/chunk-765e6480.104bef58.css
pyWebCamWebServerMonitor/web/static/css/chunk-7be6fff1.48164379.css
pyWebCamWebServerMonitor-0.0.14.dist-info/LICENSE
pyWebCamWebServerMonitor-0.0.14.dist-info/METADATA
pyWebCamWebServerMonitor-0.0.14.dist-info/WHEEL
pyWebCamWebServerMonitor-0.0.14.dist-info/entry_points.txt
pyWebCamWebServerMonitor-0.0.14.dist-info/top_level.txt
pyWebCamWebServerMonitor-0.0.14.dist-info/RECORD
