Metadata-Version: 2.1
Name: pyWebCamWebServerMonitor
Version: 0.0.14
Summary: Webcam WebControl panel build with flask & vue to record / see live and other things designed for linux.
Home-page: https://gitlab.flashsoft.eu/python/flask-pyWebCamWebMonitor
Author: Andrei O.(andrei0x309)
Author-email: andrei@flashsoft.eu
License: UNKNOWN
Keywords: webcam web control panel,webcam linux server,embedded webcam control,live streaming webcam,recording webcam
Platform: UNKNOWN
Classifier: Programming Language :: Python :: 3
Classifier: License :: OSI Approved :: MIT License
Classifier: Operating System :: POSIX :: Linux
Classifier: Framework :: Flask
Classifier: Topic :: Multimedia :: Graphics :: Capture
Classifier: Topic :: Internet :: WWW/HTTP :: WSGI :: Application
Classifier: Topic :: Multimedia
Requires-Python: >=3.6
Requires-Dist: Werkzeug (<=1.0.1)
Requires-Dist: waitress (==1.4.4)
Requires-Dist: opencv-python (<=4.3.0)
Requires-Dist: Flask (==1.1.2)
Requires-Dist: Flask-SQLAlchemy (>=2.4.4)
Requires-Dist: itsdangerous (==1.1.0)
Requires-Dist: passlib (==1.7.2)
Requires-Dist: Flask-Cors (==3.0.8)
Requires-Dist: Flask-HTTPAuth (==4.1.0)
